{
    "applications": {},
    "deterministic": true,
    "deviceType": {
        "Central Tower": {
            "applications": {
                "Luposdate3000": {
                    "REPLACE_STORE_WITH_VALUES": false,
                    "SharedMemoryDictionaryCheat": true,
                    "databaseQuery": true,
                    "databaseStore": true,
                    "mergeLocalOperatorgraphs": true,
                    "predefinedPartitionScheme": "PartitionByIDTwiceAllCollations",
                    "queryDistributionMode": "Routing",
                    "type": "Luposdate3000",
                    "useDictionaryInlineEncoding": true,
                },
                "ParkingSampleReceiver": {},
                "QueryResponseReceiver": {},
            },
            "name": "Central Tower",
            "parkingSensor": "",
            "performance": 100.0,
            "supportedLinkTypes": [
                "WPAN",
                "WLAN",
            ],
        },
        "Edge Gateway WSN 1": {
            "applications": {},
            "name": "Edge Gateway WSN 1",
            "parkingSensor": "",
            "performance": 30.0,
            "supportedLinkTypes": [
                "WPAN",
                "WLAN",
            ],
        },
        "Edge Gateway WSN 10": {
            "applications": {},
            "name": "Edge Gateway WSN 10",
            "parkingSensor": "",
            "performance": 30.0,
            "supportedLinkTypes": [
                "WPAN",
                "WLAN",
            ],
        },
        "Edge Gateway WSN 2": {
            "applications": {},
            "name": "Edge Gateway WSN 2",
            "parkingSensor": "",
            "performance": 30.0,
            "supportedLinkTypes": [
                "WPAN",
                "WLAN",
            ],
        },
        "Edge Gateway WSN 3": {
            "applications": {},
            "name": "Edge Gateway WSN 3",
            "parkingSensor": "",
            "performance": 30.0,
            "supportedLinkTypes": [
                "WPAN",
                "WLAN",
            ],
        },
        "Edge Gateway WSN 4": {
            "applications": {},
            "name": "Edge Gateway WSN 4",
            "parkingSensor": "",
            "performance": 30.0,
            "supportedLinkTypes": [
                "WPAN",
                "WLAN",
            ],
        },
        "Edge Gateway WSN 5": {
            "applications": {},
            "name": "Edge Gateway WSN 5",
            "parkingSensor": "",
            "performance": 30.0,
            "supportedLinkTypes": [
                "WPAN",
                "WLAN",
            ],
        },
        "Edge Gateway WSN 6": {
            "applications": {},
            "name": "Edge Gateway WSN 6",
            "parkingSensor": "",
            "performance": 30.0,
            "supportedLinkTypes": [
                "WPAN",
                "WLAN",
            ],
        },
        "Edge Gateway WSN 7": {
            "applications": {},
            "name": "Edge Gateway WSN 7",
            "parkingSensor": "",
            "performance": 30.0,
            "supportedLinkTypes": [
                "WPAN",
                "WLAN",
            ],
        },
        "Edge Gateway WSN 8": {
            "applications": {},
            "name": "Edge Gateway WSN 8",
            "parkingSensor": "",
            "performance": 30.0,
            "supportedLinkTypes": [
                "WPAN",
                "WLAN",
            ],
        },
        "Edge Gateway WSN 9": {
            "applications": {},
            "name": "Edge Gateway WSN 9",
            "parkingSensor": "",
            "performance": 30.0,
            "supportedLinkTypes": [
                "WPAN",
                "WLAN",
            ],
        },
        "Mesh Hop": {
            "applications": {},
            "name": "Mesh Hop",
            "parkingSensor": "",
            "performance": 20.0,
            "supportedLinkTypes": [
                "WPAN",
                "WLAN",
            ],
        },
        "Sensor Device WSN 1": {
            "applications": {},
            "name": "Sensor Device WSN 1",
            "parkingSensor": "Parking Sensor WSN 1",
            "performance": 1.0,
            "supportedLinkTypes": [
                "WPAN",
            ],
        },
        "Sensor Device WSN 10": {
            "applications": {},
            "name": "Sensor Device WSN 10",
            "parkingSensor": "Parking Sensor WSN 10",
            "performance": 1.0,
            "supportedLinkTypes": [
                "WPAN",
            ],
        },
        "Sensor Device WSN 2": {
            "applications": {},
            "name": "Sensor Device WSN 2",
            "parkingSensor": "Parking Sensor WSN 2",
            "performance": 1.0,
            "supportedLinkTypes": [
                "WPAN",
            ],
        },
        "Sensor Device WSN 3": {
            "applications": {},
            "name": "Sensor Device WSN 3",
            "parkingSensor": "Parking Sensor WSN 3",
            "performance": 1.0,
            "supportedLinkTypes": [
                "WPAN",
            ],
        },
        "Sensor Device WSN 4": {
            "applications": {},
            "name": "Sensor Device WSN 4",
            "parkingSensor": "Parking Sensor WSN 4",
            "performance": 1.0,
            "supportedLinkTypes": [
                "WPAN",
            ],
        },
        "Sensor Device WSN 5": {
            "applications": {},
            "name": "Sensor Device WSN 5",
            "parkingSensor": "Parking Sensor WSN 5",
            "performance": 1.0,
            "supportedLinkTypes": [
                "WPAN",
            ],
        },
        "Sensor Device WSN 6": {
            "applications": {},
            "name": "Sensor Device WSN 6",
            "parkingSensor": "Parking Sensor WSN 6",
            "performance": 1.0,
            "supportedLinkTypes": [
                "WPAN",
            ],
        },
        "Sensor Device WSN 7": {
            "applications": {},
            "name": "Sensor Device WSN 7",
            "parkingSensor": "Parking Sensor WSN 7",
            "performance": 1.0,
            "supportedLinkTypes": [
                "WPAN",
            ],
        },
        "Sensor Device WSN 8": {
            "applications": {},
            "name": "Sensor Device WSN 8",
            "parkingSensor": "Parking Sensor WSN 8",
            "performance": 1.0,
            "supportedLinkTypes": [
                "WPAN",
            ],
        },
        "Sensor Device WSN 9": {
            "applications": {},
            "name": "Sensor Device WSN 9",
            "parkingSensor": "Parking Sensor WSN 9",
            "performance": 1.0,
            "supportedLinkTypes": [
                "WPAN",
            ],
        },
    },
    "fixedDevice": {
        "Fog": {
            "applications": {},
            "deviceType": "Central Tower",
            "latitude": 53.83831534459554,
            "longitude": 10.698774930618905,
            "name": "Fog",
        },
        "Root WSN 1": {
            "applications": {},
            "deviceType": "Edge Gateway WSN 1",
            "latitude": 53.838474484901376,
            "longitude": 10.695081476709452,
            "name": "Root WSN 1",
        },
        "Root WSN 10": {
            "applications": {},
            "deviceType": "Edge Gateway WSN 10",
            "latitude": 53.83582633252526,
            "longitude": 10.701612267614298,
            "name": "Root WSN 10",
        },
        "Root WSN 2": {
            "applications": {},
            "deviceType": "Edge Gateway WSN 2",
            "latitude": 53.83744253948933,
            "longitude": 10.694834809499191,
            "name": "Root WSN 2",
        },
        "Root WSN 3": {
            "applications": {},
            "deviceType": "Edge Gateway WSN 3",
            "latitude": 53.836891814222774,
            "longitude": 10.697463417298081,
            "name": "Root WSN 3",
        },
        "Root WSN 4": {
            "applications": {},
            "deviceType": "Edge Gateway WSN 4",
            "latitude": 53.83862015297171,
            "longitude": 10.70005982052656,
            "name": "Root WSN 4",
        },
        "Root WSN 5": {
            "applications": {},
            "deviceType": "Edge Gateway WSN 5",
            "latitude": 53.8371134048039,
            "longitude": 10.699351680333246,
            "name": "Root WSN 5",
        },
        "Root WSN 6": {
            "applications": {},
            "deviceType": "Edge Gateway WSN 6",
            "latitude": 53.83759450606049,
            "longitude": 10.702377248379614,
            "name": "Root WSN 6",
        },
        "Root WSN 7": {
            "applications": {},
            "deviceType": "Edge Gateway WSN 7",
            "latitude": 53.83622460614883,
            "longitude": 10.697405195405576,
            "name": "Root WSN 7",
        },
        "Root WSN 8": {
            "applications": {},
            "deviceType": "Edge Gateway WSN 8",
            "latitude": 53.83523539538031,
            "longitude": 10.696438320766976,
            "name": "Root WSN 8",
        },
        "Root WSN 9": {
            "applications": {},
            "deviceType": "Edge Gateway WSN 9",
            "latitude": 53.83549953176541,
            "longitude": 10.697955598003395,
            "name": "Root WSN 9",
        },
    },
    "fixedLink": [],
    "linkType": {
        "WLAN": {
            "dataRateInKbps": 25000,
            "name": "WLAN",
            "rangeInMeters": 200,
        },
        "WPAN": {
            "dataRateInKbps": 250,
            "name": "WPAN",
            "rangeInMeters": 30,
        },
    },
    "logging": {
        "measure": {
            "enabled": false,
        },
        "stdout": {
            "enabled": false,
        },
        "visualize": {
            "enabled": false,
        },
    },
    "outputDirectory": "",
    "randomMeshNetwork": [
        {
            "deviceType": "Mesh Hop",
            "linkType": "WLAN",
            "networkPrefix": "Campus Mesh",
            "originLatitude": 53.83897140331313,
            "originLongitude": 10.694405480987202,
            "signalCoverageEast": 560,
            "signalCoverageSouth": 460,
        },
    ],
    "randomStarNetwork": [
        {
            "dataSink": "",
            "deviceType": "Sensor Device WSN 1",
            "linkType": "WPAN",
            "networkPrefix": "WSN 1",
            "number": 5,
            "starRoot": "Root WSN 1",
        },
        {
            "dataSink": "",
            "deviceType": "Sensor Device WSN 2",
            "linkType": "WPAN",
            "networkPrefix": "WSN 2",
            "number": 5,
            "starRoot": "Root WSN 2",
        },
        {
            "dataSink": "",
            "deviceType": "Sensor Device WSN 3",
            "linkType": "WPAN",
            "networkPrefix": "WSN 3",
            "number": 5,
            "starRoot": "Root WSN 3",
        },
        {
            "dataSink": "",
            "deviceType": "Sensor Device WSN 4",
            "linkType": "WPAN",
            "networkPrefix": "WSN 4",
            "number": 5,
            "starRoot": "Root WSN 4",
        },
        {
            "dataSink": "",
            "deviceType": "Sensor Device WSN 5",
            "linkType": "WPAN",
            "networkPrefix": "WSN 5",
            "number": 5,
            "starRoot": "Root WSN 5",
        },
        {
            "dataSink": "",
            "deviceType": "Sensor Device WSN 6",
            "linkType": "WPAN",
            "networkPrefix": "WSN 6",
            "number": 5,
            "starRoot": "Root WSN 6",
        },
        {
            "dataSink": "",
            "deviceType": "Sensor Device WSN 7",
            "linkType": "WPAN",
            "networkPrefix": "WSN 7",
            "number": 5,
            "starRoot": "Root WSN 7",
        },
        {
            "dataSink": "",
            "deviceType": "Sensor Device WSN 8",
            "linkType": "WPAN",
            "networkPrefix": "WSN 8",
            "number": 5,
            "starRoot": "Root WSN 8",
        },
        {
            "dataSink": "",
            "deviceType": "Sensor Device WSN 9",
            "linkType": "WPAN",
            "networkPrefix": "WSN 9",
            "number": 5,
            "starRoot": "Root WSN 9",
        },
        {
            "dataSink": "",
            "deviceType": "Sensor Device WSN 10",
            "linkType": "WPAN",
            "networkPrefix": "WSN 10",
            "number": 5,
            "starRoot": "Root WSN 10",
        },
    ],
    "rootRouter": "Fog",
    "sensorType": {
        "Parking Sensor WSN 1": {
            "area": 1,
            "dataSink": "Fog",
            "maxSamples": 3,
            "name": "Parking Sensor WSN 1",
            "rateInSec": 60,
        },
        "Parking Sensor WSN 10": {
            "area": 10,
            "dataSink": "Fog",
            "maxSamples": 3,
            "name": "Parking Sensor WSN 10",
            "rateInSec": 110,
        },
        "Parking Sensor WSN 2": {
            "area": 2,
            "dataSink": "Fog",
            "maxSamples": 3,
            "name": "Parking Sensor WSN 2",
            "rateInSec": 120,
        },
        "Parking Sensor WSN 3": {
            "area": 3,
            "dataSink": "Fog",
            "maxSamples": 3,
            "name": "Parking Sensor WSN 3",
            "rateInSec": 100,
        },
        "Parking Sensor WSN 4": {
            "area": 4,
            "dataSink": "Fog",
            "maxSamples": 3,
            "name": "Parking Sensor WSN 4",
            "rateInSec": 140,
        },
        "Parking Sensor WSN 5": {
            "area": 5,
            "dataSink": "Fog",
            "maxSamples": 3,
            "name": "Parking Sensor WSN 5",
            "rateInSec": 50,
        },
        "Parking Sensor WSN 6": {
            "area": 6,
            "dataSink": "Fog",
            "maxSamples": 3,
            "name": "Parking Sensor WSN 6",
            "rateInSec": 120,
        },
        "Parking Sensor WSN 7": {
            "area": 7,
            "dataSink": "Fog",
            "maxSamples": 3,
            "name": "Parking Sensor WSN 7",
            "rateInSec": 59,
        },
        "Parking Sensor WSN 8": {
            "area": 8,
            "dataSink": "Fog",
            "maxSamples": 3,
            "name": "Parking Sensor WSN 8",
            "rateInSec": 130,
        },
        "Parking Sensor WSN 9": {
            "area": 9,
            "dataSink": "Fog",
            "maxSamples": 3,
            "name": "Parking Sensor WSN 9",
            "rateInSec": 61,
        },
    },
}
